CHANGES.rst
LICENSE.rst
MANIFEST.in
README.rst
setup.cfg
setup.py
src/collective/__init__.py
src/collective.folderorder.egg-info/PKG-INFO
src/collective.folderorder.egg-info/SOURCES.txt
src/collective.folderorder.egg-info/dependency_links.txt
src/collective.folderorder.egg-info/entry_points.txt
src/collective.folderorder.egg-info/namespace_packages.txt
src/collective.folderorder.egg-info/not-zip-safe
src/collective.folderorder.egg-info/requires.txt
src/collective.folderorder.egg-info/top_level.txt
src/collective/folderorder/__init__.py
src/collective/folderorder/action.py
src/collective/folderorder/configure.zcml
src/collective/folderorder/form.pt
src/collective/folderorder/form.py
src/collective/folderorder/form.yaml
src/collective/folderorder/prepend.py
src/collective/folderorder/reversed.py
src/collective/folderorder/testing.py
src/collective/folderorder/locales/collective.folderorder.pot
src/collective/folderorder/locales/merge-orderings.pot
src/collective/folderorder/locales/de/LC_MESSAGES/collective.folderorder.po
src/collective/folderorder/profile/actions.xml
src/collective/folderorder/profile/metadata.xml
src/collective/folderorder/tests/__init__.py
src/collective/folderorder/tests/test_setup.py