Metadata-Version: 2.1
Name: collective.folderorder
Version: 1.4.2
Summary: Set sort order of plone folders
Home-page: http://github.com/collective/collective.folderorder
Author: Jens Klein    
Author-email: jens@bluedynamics.com
License: GPLv2
Platform: UNKNOWN
Classifier: Development Status :: 5 - Production/Stable
Classifier: License :: OSI Approved :: GNU General Public License (GPL)
Classifier: Operating System :: OS Independent
Classifier: Programming Language :: Python
Classifier: Topic :: Software Development
Classifier: Framework :: Plone
Provides-Extra: test
